pyagfs/__init__.py
pyagfs/client.py
pyagfs/exceptions.py
pyagfs/helpers.py
pyagfs-0.1.3.dist-info/METADATA
pyagfs-0.1.3.dist-info/WHEEL
pyagfs-0.1.3.dist-info/RECORD
